README.md
firefox_jar.py
setup.py
firefox_jar.egg-info/PKG-INFO
firefox_jar.egg-info/SOURCES.txt
firefox_jar.egg-info/dependency_links.txt
firefox_jar.egg-info/top_level.txt