Metadata-Version: 1.1
Name: firefox-jar
Version: 0.0.3
Summary: Load firefox cookies to CookieJar (requests compatible format).
Home-page: https://github.com/imbolc/firefox_jar
Author: Imbolc
Author-email: imbolc@imbolc.name
License: ISC
Platform: UNKNOWN
Classifier: Development Status :: 4 - Beta
Classifier: Intended Audience :: Developers
Classifier: License :: OSI Approved :: ISC License (ISCL)
Classifier: Programming Language :: Python
Classifier: Programming Language :: Python :: 3
